pytictac/__init__.py
pytictac/class_timer.py
pytictac/simple_timer.py
pytictac-1.0.9.dist-info/LICENSE
pytictac-1.0.9.dist-info/METADATA
pytictac-1.0.9.dist-info/WHEEL
pytictac-1.0.9.dist-info/top_level.txt
pytictac-1.0.9.dist-info/RECORD
