Metadata-Version: 2.1
Name: pytictac
Version: 1.0.9
Summary: A small example package
Home-page: UNKNOWN
Author: Jonas Frey
Author-email: jonfrey@ethz.ch
License: MIT
Platform: UNKNOWN
Requires-Python: >=3.6
License-File: LICENSE
